rt_logging/__init__.py
rt_logging/cli.py
rt_logging/rt_logging.py
rt_logging/tail.py
rt_logging/tee.py
ipython_rtlogging-0.2.3.dist-info/LICENSE
ipython_rtlogging-0.2.3.dist-info/METADATA
ipython_rtlogging-0.2.3.dist-info/WHEEL
ipython_rtlogging-0.2.3.dist-info/entry_points.txt
ipython_rtlogging-0.2.3.dist-info/top_level.txt
ipython_rtlogging-0.2.3.dist-info/RECORD
