Metadata-Version: 2.1
Name: ipython-rtlogging
Version: 0.2.3
Summary: real time logging via IPython
Home-page: https://github.com/wilmerwang/ipython-rtlogging
Author: wilmerwang
Author-email: 280458666@qq.com
License: UNKNOWN
Keywords: logging ipython real-time reconnection
Platform: UNKNOWN
Classifier: Programming Language :: Python :: 3
Classifier: License :: OSI Approved :: MIT License
Classifier: Operating System :: OS Independent
Requires-Dist: ipython >=8.0
Requires-Dist: rich >=13.0
